AUTHORS.txt
LICENSE.txt
MANIFEST.in
README.rst
requirements.txt
setup.py
djangocms_inline_comment/__init__.py
djangocms_inline_comment/cms_plugins.py
djangocms_inline_comment/models.py
djangocms_inline_comment.egg-info/PKG-INFO
djangocms_inline_comment.egg-info/SOURCES.txt
djangocms_inline_comment.egg-info/dependency_links.txt
djangocms_inline_comment.egg-info/requires.txt
djangocms_inline_comment.egg-info/top_level.txt
djangocms_inline_comment/migrations/0001_initial.py
djangocms_inline_comment/migrations/__init__.py
djangocms_inline_comment/templates/djangocms_inline_comment/inline_comment.html
djangocms_inline_comment/templates/djangocms_inline_comment/inline_comment_style.html
tests/__init__.py
tests/settings.py
tests/test_inline_comment.py